setup.py
HtmlProcessor/__init__.py
HtmlProcessor/grabber.py
SimpleThreading/ThreadPool.py
SimpleThreading/ThreadingByFunction.py
SimpleThreading/__init__.py
ThreadDownloader8460.egg-info/PKG-INFO
ThreadDownloader8460.egg-info/SOURCES.txt
ThreadDownloader8460.egg-info/dependency_links.txt
ThreadDownloader8460.egg-info/requires.txt
ThreadDownloader8460.egg-info/top_level.txt